demo/__init__.py
demo/common.py
demo/options_demo.py
flexbox/__init__.py
flexbox/color.py
flexbox/flex.py
flexbox/flex_flowable.py
flexbox/measurement.py
flexbox/options.py
reportlab_flexbox-0.0.4.dist-info/DESCRIPTION.rst
reportlab_flexbox-0.0.4.dist-info/METADATA
reportlab_flexbox-0.0.4.dist-info/RECORD
reportlab_flexbox-0.0.4.dist-info/WHEEL
reportlab_flexbox-0.0.4.dist-info/metadata.json
reportlab_flexbox-0.0.4.dist-info/top_level.txt
